rando_cli/__init__.py
rando_cli/rando.py
rando_cli-0.1.0.dist-info/licenses/LICENSE
rando_cli-0.1.0.dist-info/METADATA
rando_cli-0.1.0.dist-info/WHEEL
rando_cli-0.1.0.dist-info/entry_points.txt
rando_cli-0.1.0.dist-info/top_level.txt
rando_cli-0.1.0.dist-info/RECORD
