Metadata-Version: 2.4
Name: rando-cli
Version: 0.1.0
Summary: A CLI tool for generating random characters based on patterns
Home-page: https://github.com/yourusername/rando-cli
Author: Marco Kotrotsos
Author-email: your.email@example.com
Classifier: Programming Language :: Python :: 3
Classifier: License :: OSI Approved :: MIT License
Classifier: Operating System :: OS Independent
Requires-Python: >=3.6
License-File: LICENSE
Dynamic: author
Dynamic: author-email
Dynamic: classifier
Dynamic: description
Dynamic: description-content-type
Dynamic: home-page
Dynamic: license-file
Dynamic: requires-python
Dynamic: summary
